BNfinder/BDE.py
BNfinder/CrossVal.py
BNfinder/MDL.py
BNfinder/MIT.py
BNfinder/Rocr.py
BNfinder/__init__.py
BNfinder/continuous.py
BNfinder/data.py
BNfinder/graph.py
BNfinder/pstat.py
BNfinder/pyroc.py
BNfinder/score.py
BNfinder/stats.py
BNfinder/util.py
bnfinder3-3.0.0.data/scripts/bnc
bnfinder3-3.0.0.data/scripts/bnf
bnfinder3-3.0.0.data/scripts/bnf-cv
bnfinder3-3.0.0.dist-info/licenses/LICENSE
bnfinder3-3.0.0.dist-info/METADATA
bnfinder3-3.0.0.dist-info/WHEEL
bnfinder3-3.0.0.dist-info/top_level.txt
bnfinder3-3.0.0.dist-info/RECORD
